ynm3000/__init__.py
ynm3000/my_module.py
ynm3000-0.1.0.dist-info/METADATA
ynm3000-0.1.0.dist-info/WHEEL
ynm3000-0.1.0.dist-info/top_level.txt
ynm3000-0.1.0.dist-info/RECORD
