Metadata-Version: 2.1
Name: ynm3000
Version: 0.1.0
Summary: tools
Home-page: https://github.com/sunyongdi/ynm3000
Author: sunyongdi
Author-email: sunyd0305@gmail.com
License: UNKNOWN
Platform: UNKNOWN
Classifier: Development Status :: 3 - Alpha
Classifier: Intended Audience :: Developers
Classifier: License :: OSI Approved :: MIT License
Classifier: Programming Language :: Python :: 3
Classifier: Programming Language :: Python :: 3.6
Classifier: Programming Language :: Python :: 3.7
Classifier: Programming Language :: Python :: 3.8
Requires-Dist: numpy
Requires-Dist: pandas
Requires-Dist: matplotlib
